multiply/__init__.py
multiply/multiplication.py
test_ml_flow-0.2.dist-info/METADATA
test_ml_flow-0.2.dist-info/WHEEL
test_ml_flow-0.2.dist-info/top_level.txt
test_ml_flow-0.2.dist-info/RECORD
